abnf_to_plantuml/__about__.py
abnf_to_plantuml/__init__.py
abnf_to_plantuml/__main__.py
abnf_to_plantuml/base.py
abnf_to_plantuml/processing.py
abnf_to_plantuml/cli/__init__.py
abnf_to_plantuml-2.0.0.dist-info/METADATA
abnf_to_plantuml-2.0.0.dist-info/WHEEL
abnf_to_plantuml-2.0.0.dist-info/entry_points.txt
abnf_to_plantuml-2.0.0.dist-info/licenses/LICENSE.txt
abnf_to_plantuml-2.0.0.dist-info/RECORD
